<?xml version = '1.0' encoding = 'UTF-8'?>
<NFSE xmlns:ns2="http://www.w3.org/2000/09/xmldsig#" xmlns:ns3="http://www.ginfes.com.br/tipos" xmlns:ns4="http://www.ginfes.com.br/servico_consultar_nfse_envio" xmlns:ns5="http://www.ginfes.com.br/servico_cancelar_nfse_envio">
<Nfse>
<ns3:IdentificacaoNfse>
<ns3:Numero>7865</ns3:Numero>
<ns3:CodigoVerificacao>183843672</ns3:CodigoVerificacao>
</ns3:IdentificacaoNfse>
<ns3:DataEmissao>2012-04-11T10:51:01</ns3:DataEmissao>
<ns3:IdentificacaoRps>
<ns3:Numero>201200000007905</ns3:Numero>
<ns3:Serie>1</ns3:Serie>
<ns3:Tipo>1</ns3:Tipo>
</ns3:IdentificacaoRps>
<ns3:DataEmissaoRps>2012-04-11T10:40:23</ns3:DataEmissaoRps>
<ns3:NaturezaOperacao>1</ns3:NaturezaOperacao>
<ns3:RegimeEspecialTributacao>0</ns3:RegimeEspecialTributacao>
<ns3:OptanteSimplesNacional>2</ns3:OptanteSimplesNacional>
<ns3:IncetivadorCultural>2</ns3:IncetivadorCultural>
<ns3:Competencia>2012-04-01</ns3:Competencia>
<ns3:Servico>
<ns3:Valores>
<ns3:ValorServicos>323.15</ns3:ValorServicos>
<ns3:ValorPis>0.00</ns3:ValorPis>
<ns3:ValorCofins>0.00</ns3:ValorCofins>
<ns3:IssRetido>2</ns3:IssRetido>
<ns3:ValorIss>6.46</ns3:ValorIss>
<ns3:BaseCalculo>323.15</ns3:BaseCalculo>
<ns3:Aliquota>0.0200</ns3:Aliquota>
<ns3:ValorLiquidoNfse>323.15</ns3:ValorLiquidoNfse>
</ns3:Valores>
<ns3:ItemListaServico>106</ns3:ItemListaServico>
<ns3:CodigoTributacaoMunicipio>1185</ns3:CodigoTributacaoMunicipio>
<ns3:Discriminacao>LICENCA DE USO MENSAL DO SOFTWARE TEF</ns3:Discriminacao>
<ns3:MunicipioPrestacaoServico>3525904</ns3:MunicipioPrestacaoServico>
</ns3:Servico>
<ns3:ValorCredito>0.00</ns3:ValorCredito>
<ns3:PrestadorServico>
<ns3:IdentificacaoPrestador>
<ns3:Cnpj>00865547000150</ns3:Cnpj>
<ns3:InscricaoMunicipal>51709</ns3:InscricaoMunicipal>
</ns3:IdentificacaoPrestador>
<ns3:RazaoSocial>GZ SISTEMAS IMPORTACAO COMERCIO LTD</ns3:RazaoSocial>
<ns3:NomeFantasia>G.Z.</ns3:NomeFantasia>
<ns3:Endereco>
<ns3:Endereco>MARECHAL DEODORO DA FONSECA</ns3:Endereco>
<ns3:Numero>736</ns3:Numero>
<ns3:Complemento>PAV SUPERIOR</ns3:Complemento>
<ns3:Bairro>CENTRO</ns3:Bairro>
<ns3:Cidade>3525904</ns3:Cidade>
<ns3:Estado>SP</ns3:Estado>
<ns3:Cep>13201002</ns3:Cep>
</ns3:Endereco>
<ns3:Contato>
<ns3:Telefone>1133088199</ns3:Telefone>
<ns3:Email>nfe@gzsistemas.com.br</ns3:Email>
</ns3:Contato>
</ns3:PrestadorServico>
<ns3:TomadorServico>
<ns3:IdentificacaoTomador>
<ns3:CpfCnpj>
<ns3:Cnpj>45099645000161</ns3:Cnpj>
</ns3:CpfCnpj>
</ns3:IdentificacaoTomador>
<ns3:RazaoSocial>SUPERMERCADO TRIDICO LTDA</ns3:RazaoSocial>
<ns3:Endereco>
<ns3:Endereco>RUA PROF OSCAR PIRES</ns3:Endereco>
<ns3:Numero>926</ns3:Numero>
<ns3:Bairro>PQ INDUSTRIAL</ns3:Bairro>
<ns3:Cidade>3549805</ns3:Cidade>
<ns3:Estado>SP</ns3:Estado>
<ns3:Cep>15030530</ns3:Cep>
</ns3:Endereco>
<ns3:Contato>
<ns3:Email>neia_orlando@hotmail.com</ns3:Email>
</ns3:Contato>
</ns3:TomadorServico>
<ns3:OrgaoGerador>
<ns3:CodigoMunicipio>3525904</ns3:CodigoMunicipio>
<ns3:Uf>SP</ns3:Uf>
</ns3:OrgaoGerador>
</Nfse>
</NFSE>